{
  "title": "Cir Mhòr and Ceum na Caillich From Glen Rosa",
  "meta": {
    "location": "Glen Rosa",
    "tags": [
      "Landscape"
    ],
    "trip": "2025-05-08-isle-of-arran"
  },
  "exif": {
    "camera": {
      "name": "Sony ɑ7R V",
      "lens": "Sony FE 100-400mm GM",
      "settings": {
        "exposureBias": 0,
        "exposureTime": 0.004,
        "focalLength": 100,
        "fStop": 4.5,
        "ISO": 100
      }
    },
    "date": "2025-05-09T09:24:09.000+01:00",
    "dimensions": {
      "height": 6116,
      "width": 9174
    }
  }
}