{
  "title": "Following the Forest Path",
  "meta": {
    "location": "Puck's Glen",
    "tags": [
      "Landscape",
      "Forest"
    ],
    "trip": "2023-06-24-isle-of-bute"
  },
  "exif": {
    "camera": {
      "name": "Sony ɑ7R V",
      "lens": "Sony FE 24-70mm F2.8 GM II",
      "settings": {
        "exposureBias": 0,
        "exposureTime": 0.25,
        "focalLength": 60,
        "fStop": 22,
        "ISO": 12800
      }
    },
    "date": "2023-06-25T09:41:29.000+01:00",
    "dimensions": {
      "height": 6336,
      "width": 9504
    }
  }
}