{
  "title": "Harter Fell (Mardale)",
  "meta": {
    "location": "Harter Fell (Mardale)",
    "tags": [
      "Landscape",
      "Cairn",
      "Wainwright"
    ],
    "trip": "2025-04-17-lake-district"
  },
  "exif": {
    "camera": {
      "name": "Sony ɑ7R V",
      "lens": "Sony FE 24-70mm F2.8 GM II",
      "settings": {
        "exposureBias": 0,
        "exposureTime": 0.00625,
        "focalLength": 70,
        "fStop": 8,
        "ISO": 100
      }
    },
    "date": "2025-04-20T13:01:05.000+01:00",
    "dimensions": {
      "height": 5694,
      "width": 8542
    }
  },
  "settings": {
    "showPhoto": true
  }
}