{
  "title": "High Rigg Fence",
  "meta": {
    "location": "High Rigg",
    "tags": [
      "Landscape",
      "Snow"
    ],
    "trip": "2025-11-21-latrigg-high-rigg"
  },
  "exif": {
    "camera": {
      "name": "Sony ɑ7R V",
      "lens": "Sony FE 24-70mm F2.8 GM II",
      "settings": {
        "exposureBias": 0,
        "exposureTime": 0.016666666666666666,
        "focalLength": 31,
        "fStop": 8,
        "ISO": 100
      }
    },
    "date": "2025-11-21T11:42:39.000+00:00",
    "dimensions": {
      "height": 5749,
      "width": 8624
    }
  }
}