{
  "title": "Lagavulin Still Room",
  "meta": {
    "location": "Lagavulin",
    "tags": [
      "Interior"
    ],
    "trip": null
  },
  "exif": {
    "date": "2024-04-13T16:02:45.000+01:00",
    "dimensions": {
      "height": 6336,
      "width": 9504
    },
    "camera": {
      "name": "Sony ɑ7R V",
      "lens": "Sony FE 24-70mm F2.8 GM II",
      "settings": {
        "exposureBias": -0.7,
        "exposureTime": 0.03333333333333333,
        "focalLength": 24,
        "fStop": 2.8,
        "ISO": 400
      }
    }
  }
}