{
  "title": "Old Man of Hoy From the Ferry",
  "meta": {
    "location": "Orkney",
    "tags": [
      "Landscape",
      "Coast"
    ],
    "trip": "2025-06-13-orkney"
  },
  "exif": {
    "camera": {
      "name": "Sony ɑ7R V",
      "lens": "Sony FE 100-400mm GM",
      "settings": {
        "exposureBias": 0,
        "exposureTime": 0.025,
        "focalLength": 200,
        "fStop": 5.6,
        "ISO": 125
      }
    },
    "date": "2025-06-14T09:51:17.000+01:00",
    "dimensions": {
      "height": 5865,
      "width": 8798
    }
  }
}