{
  "title": "Raby Castle Christmas Tree Ornaments",
  "meta": {
    "location": "Raby Castle",
    "tags": [],
    "trip": "2025-12-29-raby-castle"
  },
  "exif": {
    "camera": {
      "name": "Sony ɑ7R V",
      "lens": "Sony FE 24-70mm F2.8 GM II",
      "settings": {
        "exposureBias": -0.3,
        "exposureTime": 0.2,
        "focalLength": 62,
        "fStop": 4,
        "ISO": 500
      }
    },
    "date": "2025-12-29T11:28:54.000+00:00",
    "dimensions": {
      "height": 5595,
      "width": 8393
    }
  }
}