{
  "title": "Sea of the Hebrides Sun Rays",
  "meta": {
    "location": "Ben Feall",
    "tags": [
      "Landscape",
      "Coast"
    ],
    "trip": null
  },
  "exif": {
    "date": "2024-05-25T20:20:34.000+01:00",
    "dimensions": {
      "height": 6304,
      "width": 9457
    },
    "camera": {
      "name": "Sony ɑ7R V",
      "lens": "Sony FE 24-70mm F2.8 GM II",
      "settings": {
        "exposureBias": -0.7,
        "exposureTime": 0.00015624999650578762,
        "focalLength": 70,
        "fStop": 2.8,
        "ISO": 100
      }
    }
  }
}