{
  "title": "Sunset Over Höfn",
  "meta": {
    "location": "Hornafjörður",
    "tags": [
      "Landscape",
      "Snow",
      "Sunrise/Sunset"
    ],
    "trip": "2024-08-24-iceland"
  },
  "exif": {
    "camera": {
      "name": "Sony ɑ7R V",
      "lens": "Sony FE 100-400mm F4.5-5.6 OSS",
      "settings": {
        "exposureBias": 0.3,
        "exposureTime": 0.005,
        "focalLength": 198,
        "fStop": 5.6,
        "ISO": 500
      }
    },
    "date": "2024-08-25T20:26:01.000+01:00",
    "dimensions": {
      "height": 5158,
      "width": 7737
    }
  }
}